mandalorian/__init__.py
mandalorian-0.0.2.dist-info/LICENSE
mandalorian-0.0.2.dist-info/METADATA
mandalorian-0.0.2.dist-info/WHEEL
mandalorian-0.0.2.dist-info/top_level.txt
mandalorian-0.0.2.dist-info/RECORD
