Metadata-Version: 2.1
Name: mandalorian
Version: 0.0.2
Summary: nand2tetris CLI helper utils
Home-page: https://github.com/samarthdave/mando
Author: Cameron Brill
Author-email: contact@cameronbrill.me
License: UNKNOWN
Platform: UNKNOWN
Classifier: Programming Language :: Python :: 3
Classifier: License :: OSI Approved :: MIT License
Classifier: Operating System :: OS Independent
Requires-Python: >=3.7
